mikumotion/__init__.py
mikumotion/blender.py
mikumotion/math.py
mikumotion/motion_sequence.py
mikumotion/presets.py
mikumotion-2025.7.25.dist-info/licenses/LICENSE
mikumotion-2025.7.25.dist-info/METADATA
mikumotion-2025.7.25.dist-info/WHEEL
mikumotion-2025.7.25.dist-info/top_level.txt
mikumotion-2025.7.25.dist-info/RECORD
