Metadata-Version: 2.4
Name: mikumotion
Version: 2025.7.25
Author-email: "-T.K.-" <tk233.xyz@gmail.com>
Project-URL: Source, https://github.com/T-K-233/MikuMotionTools
Project-URL: Tracker, https://github.com/T-K-233/MikuMotionTools/issues
Keywords: motion,mmd,blender
Classifier: Programming Language :: Python :: 3
Classifier: License :: OSI Approved :: MIT License
Classifier: Operating System :: OS Independent
Requires-Python: >=3.8
License-File: LICENSE
Requires-Dist: numpy
Requires-Dist: mujoco
Requires-Dist: mink
Provides-Extra: examples
Requires-Dist: loop-rate-limiters>=0.1.0; extra == "examples"
Requires-Dist: qpsolvers[daqp]>=4.3.1; extra == "examples"
Requires-Dist: osqp<1,>=0.6.2; extra == "examples"
Requires-Dist: matplotlib; extra == "examples"
Provides-Extra: all
Requires-Dist: mikumotion[examples]; extra == "all"
Dynamic: license-file
